metlinkpid.py
metlinkpid-1.0.2.dist-info/LICENSE
metlinkpid-1.0.2.dist-info/METADATA
metlinkpid-1.0.2.dist-info/WHEEL
metlinkpid-1.0.2.dist-info/top_level.txt
metlinkpid-1.0.2.dist-info/RECORD
