Metadata-Version: 2.1
Name: metlinkpid
Version: 1.0.2
Summary: Metlink LED passenger information display driver
Home-page: https://github.com/Lx/python-metlinkpid
Author: Alex Peters
License: UNKNOWN
Platform: UNKNOWN
Classifier: Development Status :: 5 - Production/Stable
Classifier: License :: OSI Approved :: MIT License
Classifier: Natural Language :: English
Classifier: Operating System :: OS Independent
Classifier: Programming Language :: Python :: 3.6
Classifier: Programming Language :: Python :: 3.7
Classifier: Typing :: Typed
Requires-Python: ~=3.6
Requires-Dist: attrs
Requires-Dist: dlestxetx
Requires-Dist: crccheck
Requires-Dist: pyserial
Provides-Extra: docs
Requires-Dist: sphinx (~=2.1.1) ; extra == 'docs'
Requires-Dist: sphinx-rtd-theme (~=0.4.3) ; extra == 'docs'
